Metadata-Version: 2.1
Name: drf-dumas
Version: 0.0.1
Summary: tiny utils for DRF
Home-page: https://github.com/frangte/dumas
Author: nakhoa
Author-email: nakhoa17@gmail.com
License: UNKNOWN
Platform: UNKNOWN
Classifier: Programming Language :: Python :: 3
Classifier: License :: OSI Approved :: MIT License
Classifier: Operating System :: OS Independent
Requires-Python: >=3.6
